ovos_audio_plugin_simple/__init__.py
ovos_audio_plugin_simple/version.py
ovos_audio_plugin_simple-0.1.3.dist-info/licenses/LICENSE
ovos_audio_plugin_simple-0.1.3.dist-info/METADATA
ovos_audio_plugin_simple-0.1.3.dist-info/WHEEL
ovos_audio_plugin_simple-0.1.3.dist-info/entry_points.txt
ovos_audio_plugin_simple-0.1.3.dist-info/top_level.txt
ovos_audio_plugin_simple-0.1.3.dist-info/RECORD
