Metadata-Version: 2.4
Name: ovos_audio_plugin_simple
Version: 0.1.3
Summary: simple audio plugin for ovos
Home-page: https://github.com/OpenVoiceOS/ovos-audio-plugin-simple
Author: jarbasAi
Author-email: jarbasai@mailfence.com
License: Apache-2.0
Keywords: ovos audio plugin
License-File: LICENSE
Requires-Dist: ovos-plugin-manager<3.0.0,>=0.0.1
Dynamic: author
Dynamic: author-email
Dynamic: home-page
Dynamic: keywords
Dynamic: license
Dynamic: license-file
Dynamic: requires-dist
Dynamic: summary
